growthTool/API.py
growthTool/GUI_loadModels.py
growthTool/GUI_mainGrowthTool.py
growthTool/GUI_update_message.py
growthTool/Manager.py
growthTool/ModelObject.py
growthTool/MplCanvas.py
growthTool/MySQLRead.py
growthTool/STDCleaner.py
growthTool/__init__.py
growthTool/automatedDecision.py
growthTool/blockInfo.py
growthTool/modelsFunctions.py
growthTool/queries.py
growthTool/redFlag.py
growthTool/saveApp.py
growthTool/settings.py
growthTool-1.0.0.dist-info/LICENSE
growthTool-1.0.0.dist-info/METADATA
growthTool-1.0.0.dist-info/WHEEL
growthTool-1.0.0.dist-info/top_level.txt
growthTool-1.0.0.dist-info/RECORD
